{"title":"URDF 导出资料（ROS2）","slug":"code/ros2/ros2_urdf","date":"2023-08-21T11:05:00.000Z","updated":"2023-08-21T11:05:00.000Z","comments":true,"path":"api/articles/code/ros2/ros2_urdf.json","excerpt":null,"covers":["https://img.undf.top/image/ros2_urdf/20230821145339-2023-08-21.png","https://img.undf.top/image/ros2_urdf/20230821150216-2023-08-21.png","https://img.undf.top/image/ros2_urdf/20230821150418-2023-08-21.png","https://img.undf.top/image/ros2_urdf/20230821150631-2023-08-21.png","https://img.undf.top/image/ros2_urdf/20230821151342-2023-08-21.png","https://img.undf.top/image/ros2_urdf/20230821151701-2023-08-21.png","https://img.undf.top/image/ros2_urdf/%E8%BD%A8%E8%BF%B9%E8%A7%84%E5%88%92-2023-08-21.gif"],"content":"<h2 id=\"坐标系建立\"><a href=\"#坐标系建立\" class=\"headerlink\" title=\"坐标系建立\"></a>坐标系建立</h2><p><img src=\"https://img.undf.top/image/ros2_urdf/20230821145339-2023-08-21.png\" alt=\"20230821145339-2023-08-21\"></p>\n<p>如图所示按照DH坐标法建立各个坐标系</p>\n<p>坐标系建立方法去复习机器人导论</p>\n<p>建立完成可能会很乱 不用担心</p>\n<h2 id=\"插件安装和使用\"><a href=\"#插件安装和使用\" class=\"headerlink\" title=\"插件安装和使用\"></a>插件安装和使用</h2><p><a href=\"https://github.com/ros/solidworks_urdf_exporter\">插件下载地址</a></p>\n<p>经测试 1.6.1支持 solidworks 2022 sp5（实验室当前使用的版本）</p>\n<p>warning: 插件要在装配体里面才有反应</p>\n<h3 id=\"插件使用\"><a href=\"#插件使用\" class=\"headerlink\" title=\"插件使用\"></a>插件使用</h3><p>打开插件</p>\n<p><img src=\"https://img.undf.top/image/ros2_urdf/20230821150216-2023-08-21.png\" alt=\"20230821150216-2023-08-21\"></p>\n<p>base_link </p>\n<p><img src=\"https://img.undf.top/image/ros2_urdf/20230821150418-2023-08-21.png\" alt=\"20230821150418-2023-08-21\"></p>\n<p>normal_link</p>\n<p><img src=\"https://img.undf.top/image/ros2_urdf/20230821150631-2023-08-21.png\" alt=\"20230821150631-2023-08-21\"></p>\n<p>其中关节类型如下</p>\n<table>\n<thead>\n<tr>\n<th>关节类型</th>\n<th>描述</th>\n</tr>\n</thead>\n<tbody><tr>\n<td>continuous</td>\n<td>旋转关节，可以围绕单轴无限旋转</td>\n</tr>\n<tr>\n<td>revolute</td>\n<td>旋转关节，类似于continuous,.但是有旋转的角度极限  <strong>一定要设置上下限不然默认为0</strong></td>\n</tr>\n<tr>\n<td>prismatic</td>\n<td>滑动关节，沿某一轴线移动的关节，带有位置极限</td>\n</tr>\n<tr>\n<td>plannar</td>\n<td>平面关节，允许在平面正交方向上平移或者旋转</td>\n</tr>\n<tr>\n<td>floating</td>\n<td>浮动关节，允许进行平移、旋转运动</td>\n</tr>\n<tr>\n<td>fixed</td>\n<td>固定关节，不允许运动的特殊关节</td>\n</tr>\n</tbody></table>\n<p>设置完成后单击导出按钮</p>\n<p><img src=\"https://img.undf.top/image/ros2_urdf/20230821151342-2023-08-21.png\" alt=\"20230821151342-2023-08-21\"></p>\n<p><img src=\"https://img.undf.top/image/ros2_urdf/20230821151701-2023-08-21.png\" alt=\"20230821151701-2023-08-21\"></p>\n<p>导出即可</p>\n<p>注意导出名即为ros中的包名，勿乱写</p>\n<h2 id=\"URDF-测试\"><a href=\"#URDF-测试\" class=\"headerlink\" title=\"URDF 测试\"></a>URDF 测试</h2><p>CoppeliaSim Edu 导入URDF 简单拖动旋转测试一下</p>\n<h2 id=\"URDF-文件包修改\"><a href=\"#URDF-文件包修改\" class=\"headerlink\" title=\"URDF 文件包修改\"></a>URDF 文件包修改</h2><h3 id=\"修改CMakelist-txt\"><a href=\"#修改CMakelist-txt\" class=\"headerlink\" title=\"修改CMakelist.txt\"></a>修改CMakelist.txt</h3><p>根据自己的情况修改</p>\n<figure class=\"highlight cmake\"><table><tr><td class=\"gutter\"><pre><span class=\"line\">1</span><br><span class=\"line\">2</span><br><span class=\"line\">3</span><br><span class=\"line\">4</span><br><span class=\"line\">5</span><br><span class=\"line\">6</span><br><span class=\"line\">7</span><br></pre></td><td class=\"code\"><pre><span class=\"line\"><span class=\"keyword\">cmake_minimum_required</span>(VERSION <span class=\"number\">3.10</span>.<span class=\"number\">2</span>)</span><br><span class=\"line\"><span class=\"keyword\">project</span>(moveit_resources_fanuc_description) <span class=\"comment\"># 修改为自己的包名</span></span><br><span class=\"line\"><span class=\"keyword\">find_package</span>(ament_cmake REQUIRED)</span><br><span class=\"line\"></span><br><span class=\"line\">ament_package()</span><br><span class=\"line\"></span><br><span class=\"line\"><span class=\"keyword\">install</span>(DIRECTORY meshes urdf DESTINATION share/<span class=\"variable\">$&#123;PROJECT_NAME&#125;</span>)</span><br></pre></td></tr></table></figure>\n<h3 id=\"修改package-xml\"><a href=\"#修改package-xml\" class=\"headerlink\" title=\"修改package.xml\"></a>修改package.xml</h3><figure class=\"highlight xml\"><table><tr><td class=\"gutter\"><pre><span class=\"line\">1</span><br><span class=\"line\">2</span><br><span class=\"line\">3</span><br><span class=\"line\">4</span><br><span class=\"line\">5</span><br><span class=\"line\">6</span><br><span class=\"line\">7</span><br><span class=\"line\">8</span><br><span class=\"line\">9</span><br><span class=\"line\">10</span><br><span class=\"line\">11</span><br><span class=\"line\">12</span><br><span class=\"line\">13</span><br><span class=\"line\">14</span><br><span class=\"line\">15</span><br><span class=\"line\">16</span><br><span class=\"line\">17</span><br><span class=\"line\">18</span><br><span class=\"line\">19</span><br><span class=\"line\">20</span><br><span class=\"line\">21</span><br></pre></td><td class=\"code\"><pre><span class=\"line\"><span class=\"meta\">&lt;?xml version=<span class=\"string\">&quot;1.0&quot;</span>?&gt;</span></span><br><span class=\"line\"><span class=\"tag\">&lt;<span class=\"name\">package</span> <span class=\"attr\">format</span>=<span class=\"string\">&quot;3&quot;</span>&gt;</span></span><br><span class=\"line\">  <span class=\"comment\">&lt;!-- # 根据内容修改 --&gt;</span></span><br><span class=\"line\">  <span class=\"tag\">&lt;<span class=\"name\">name</span>&gt;</span>moveit_resources_panda_description<span class=\"tag\">&lt;/<span class=\"name\">name</span>&gt;</span> </span><br><span class=\"line\"></span><br><span class=\"line\">  <span class=\"tag\">&lt;<span class=\"name\">version</span>&gt;</span>2.0.6<span class=\"tag\">&lt;/<span class=\"name\">version</span>&gt;</span></span><br><span class=\"line\">  <span class=\"tag\">&lt;<span class=\"name\">description</span>&gt;</span>panda Resources used for MoveIt testing<span class=\"tag\">&lt;/<span class=\"name\">description</span>&gt;</span></span><br><span class=\"line\"></span><br><span class=\"line\">  <span class=\"tag\">&lt;<span class=\"name\">author</span> <span class=\"attr\">email</span>=<span class=\"string\">&quot;isucan@willowgarage.edu&quot;</span>&gt;</span>Ioan Sucan<span class=\"tag\">&lt;/<span class=\"name\">author</span>&gt;</span></span><br><span class=\"line\">  <span class=\"tag\">&lt;<span class=\"name\">author</span> <span class=\"attr\">email</span>=<span class=\"string\">&quot;acorn@willowgarage.edu&quot;</span>&gt;</span>Acorn Pooley<span class=\"tag\">&lt;/<span class=\"name\">author</span>&gt;</span></span><br><span class=\"line\"></span><br><span class=\"line\">  <span class=\"tag\">&lt;<span class=\"name\">maintainer</span> <span class=\"attr\">email</span>=<span class=\"string\">&quot;dave@dav.ee&quot;</span>&gt;</span>Dave Coleman<span class=\"tag\">&lt;/<span class=\"name\">maintainer</span>&gt;</span></span><br><span class=\"line\"></span><br><span class=\"line\">  <span class=\"tag\">&lt;<span class=\"name\">license</span>&gt;</span>BSD<span class=\"tag\">&lt;/<span class=\"name\">license</span>&gt;</span></span><br><span class=\"line\"></span><br><span class=\"line\">  <span class=\"tag\">&lt;<span class=\"name\">buildtool_depend</span>&gt;</span>ament_cmake<span class=\"tag\">&lt;/<span class=\"name\">buildtool_depend</span>&gt;</span></span><br><span class=\"line\"></span><br><span class=\"line\">  <span class=\"tag\">&lt;<span class=\"name\">export</span>&gt;</span></span><br><span class=\"line\">      <span class=\"tag\">&lt;<span class=\"name\">build_type</span>&gt;</span>ament_cmake<span class=\"tag\">&lt;/<span class=\"name\">build_type</span>&gt;</span></span><br><span class=\"line\">  <span class=\"tag\">&lt;/<span class=\"name\">export</span>&gt;</span></span><br><span class=\"line\"><span class=\"tag\">&lt;/<span class=\"name\">package</span>&gt;</span></span><br></pre></td></tr></table></figure>\n\n<h3 id=\"编译包\"><a href=\"#编译包\" class=\"headerlink\" title=\"编译包\"></a>编译包</h3><p>将包放入 ros2 或者 moveit2 工作空间中</p>\n<figure class=\"highlight bash\"><table><tr><td class=\"gutter\"><pre><span class=\"line\">1</span><br></pre></td><td class=\"code\"><pre><span class=\"line\">colcon build --packages-select moveit_resources_fanuc_description <span class=\"comment\"># 修改为自己的包名</span></span><br></pre></td></tr></table></figure>\n\n<h2 id=\"MoveIt-Setup-Assistant-配置\"><a href=\"#MoveIt-Setup-Assistant-配置\" class=\"headerlink\" title=\"MoveIt Setup Assistant 配置\"></a>MoveIt Setup Assistant 配置</h2><figure class=\"highlight bash\"><table><tr><td class=\"gutter\"><pre><span class=\"line\">1</span><br><span class=\"line\">2</span><br><span class=\"line\">3</span><br><span class=\"line\">4</span><br><span class=\"line\">5</span><br><span class=\"line\">6</span><br><span class=\"line\">7</span><br></pre></td><td class=\"code\"><pre><span class=\"line\"><span class=\"comment\"># 激活ros2环境</span></span><br><span class=\"line\"><span class=\"built_in\">source</span> /opt/ros/foxy/setup.bash</span><br><span class=\"line\"><span class=\"comment\"># 激活moveit环境</span></span><br><span class=\"line\"><span class=\"built_in\">source</span> ~/moveit2_ws/install/setup.bash <span class=\"comment\"># 刚才编译包的路径</span></span><br><span class=\"line\"><span class=\"comment\"># 启动moveit  MoveIt Setup Assistant</span></span><br><span class=\"line\">ros2 launch moveit_setup_assistant setup_assistant.launch.py</span><br><span class=\"line\"></span><br></pre></td></tr></table></figure>\n\n<p>剩下的就参照<a href=\"https://moveit.picknik.ai/main/doc/examples/setup_assistant/setup_assistant_tutorial.html\">官网文档</a></p>\n<h2 id=\"演示\"><a href=\"#演示\" class=\"headerlink\" title=\"演示\"></a>演示</h2><figure class=\"highlight bash\"><table><tr><td class=\"gutter\"><pre><span class=\"line\">1</span><br><span class=\"line\">2</span><br></pre></td><td class=\"code\"><pre><span class=\"line\"><span class=\"comment\"># 运行演示</span></span><br><span class=\"line\">ros2 launch panda_moveit_config demo.launch.py <span class=\"comment\"># 修改为自己的包名</span></span><br></pre></td></tr></table></figure>\n\n<p><img src=\"https://img.undf.top/image/ros2_urdf/%E8%BD%A8%E8%BF%B9%E8%A7%84%E5%88%92-2023-08-21.gif\" alt=\"轨迹规划-2023-08-21\"></p>\n<h2 id=\"其他\"><a href=\"#其他\" class=\"headerlink\" title=\"其他\"></a>其他</h2><p>我在导出复杂模型时遇到一些问题，可能是插件的问题，导出的模型有些问题，但是简单模型没有问题</p>\n<p>经过CoppeliaSim Edu导入再导出，可以解决这个问题（记得修改urdf内的文件路径）</p>\n","more":"<h2 id=\"坐标系建立\"><a href=\"#坐标系建立\" class=\"headerlink\" title=\"坐标系建立\"></a>坐标系建立</h2><p><img src=\"https://img.undf.top/image/ros2_urdf/20230821145339-2023-08-21.png\" alt=\"20230821145339-2023-08-21\"></p>\n<p>如图所示按照DH坐标法建立各个坐标系</p>\n<p>坐标系建立方法去复习机器人导论</p>\n<p>建立完成可能会很乱 不用担心</p>\n<h2 id=\"插件安装和使用\"><a href=\"#插件安装和使用\" class=\"headerlink\" title=\"插件安装和使用\"></a>插件安装和使用</h2><p><a href=\"https://github.com/ros/solidworks_urdf_exporter\">插件下载地址</a></p>\n<p>经测试 1.6.1支持 solidworks 2022 sp5（实验室当前使用的版本）</p>\n<p>warning: 插件要在装配体里面才有反应</p>\n<h3 id=\"插件使用\"><a href=\"#插件使用\" class=\"headerlink\" title=\"插件使用\"></a>插件使用</h3><p>打开插件</p>\n<p><img src=\"https://img.undf.top/image/ros2_urdf/20230821150216-2023-08-21.png\" alt=\"20230821150216-2023-08-21\"></p>\n<p>base_link </p>\n<p><img src=\"https://img.undf.top/image/ros2_urdf/20230821150418-2023-08-21.png\" alt=\"20230821150418-2023-08-21\"></p>\n<p>normal_link</p>\n<p><img src=\"https://img.undf.top/image/ros2_urdf/20230821150631-2023-08-21.png\" alt=\"20230821150631-2023-08-21\"></p>\n<p>其中关节类型如下</p>\n<table>\n<thead>\n<tr>\n<th>关节类型</th>\n<th>描述</th>\n</tr>\n</thead>\n<tbody><tr>\n<td>continuous</td>\n<td>旋转关节，可以围绕单轴无限旋转</td>\n</tr>\n<tr>\n<td>revolute</td>\n<td>旋转关节，类似于continuous,.但是有旋转的角度极限  <strong>一定要设置上下限不然默认为0</strong></td>\n</tr>\n<tr>\n<td>prismatic</td>\n<td>滑动关节，沿某一轴线移动的关节，带有位置极限</td>\n</tr>\n<tr>\n<td>plannar</td>\n<td>平面关节，允许在平面正交方向上平移或者旋转</td>\n</tr>\n<tr>\n<td>floating</td>\n<td>浮动关节，允许进行平移、旋转运动</td>\n</tr>\n<tr>\n<td>fixed</td>\n<td>固定关节，不允许运动的特殊关节</td>\n</tr>\n</tbody></table>\n<p>设置完成后单击导出按钮</p>\n<p><img src=\"https://img.undf.top/image/ros2_urdf/20230821151342-2023-08-21.png\" alt=\"20230821151342-2023-08-21\"></p>\n<p><img src=\"https://img.undf.top/image/ros2_urdf/20230821151701-2023-08-21.png\" alt=\"20230821151701-2023-08-21\"></p>\n<p>导出即可</p>\n<p>注意导出名即为ros中的包名，勿乱写</p>\n<h2 id=\"URDF-测试\"><a href=\"#URDF-测试\" class=\"headerlink\" title=\"URDF 测试\"></a>URDF 测试</h2><p>CoppeliaSim Edu 导入URDF 简单拖动旋转测试一下</p>\n<h2 id=\"URDF-文件包修改\"><a href=\"#URDF-文件包修改\" class=\"headerlink\" title=\"URDF 文件包修改\"></a>URDF 文件包修改</h2><h3 id=\"修改CMakelist-txt\"><a href=\"#修改CMakelist-txt\" class=\"headerlink\" title=\"修改CMakelist.txt\"></a>修改CMakelist.txt</h3><p>根据自己的情况修改</p>\n<figure class=\"highlight cmake\"><table><tr><td class=\"gutter\"><pre><span class=\"line\">1</span><br><span class=\"line\">2</span><br><span class=\"line\">3</span><br><span class=\"line\">4</span><br><span class=\"line\">5</span><br><span class=\"line\">6</span><br><span class=\"line\">7</span><br></pre></td><td class=\"code\"><pre><span class=\"line\"><span class=\"keyword\">cmake_minimum_required</span>(VERSION <span class=\"number\">3.10</span>.<span class=\"number\">2</span>)</span><br><span class=\"line\"><span class=\"keyword\">project</span>(moveit_resources_fanuc_description) <span class=\"comment\"># 修改为自己的包名</span></span><br><span class=\"line\"><span class=\"keyword\">find_package</span>(ament_cmake REQUIRED)</span><br><span class=\"line\"></span><br><span class=\"line\">ament_package()</span><br><span class=\"line\"></span><br><span class=\"line\"><span class=\"keyword\">install</span>(DIRECTORY meshes urdf DESTINATION share/<span class=\"variable\">$&#123;PROJECT_NAME&#125;</span>)</span><br></pre></td></tr></table></figure>\n<h3 id=\"修改package-xml\"><a href=\"#修改package-xml\" class=\"headerlink\" title=\"修改package.xml\"></a>修改package.xml</h3><figure class=\"highlight xml\"><table><tr><td class=\"gutter\"><pre><span class=\"line\">1</span><br><span class=\"line\">2</span><br><span class=\"line\">3</span><br><span class=\"line\">4</span><br><span class=\"line\">5</span><br><span class=\"line\">6</span><br><span class=\"line\">7</span><br><span class=\"line\">8</span><br><span class=\"line\">9</span><br><span class=\"line\">10</span><br><span class=\"line\">11</span><br><span class=\"line\">12</span><br><span class=\"line\">13</span><br><span class=\"line\">14</span><br><span class=\"line\">15</span><br><span class=\"line\">16</span><br><span class=\"line\">17</span><br><span class=\"line\">18</span><br><span class=\"line\">19</span><br><span class=\"line\">20</span><br><span class=\"line\">21</span><br></pre></td><td class=\"code\"><pre><span class=\"line\"><span class=\"meta\">&lt;?xml version=<span class=\"string\">&quot;1.0&quot;</span>?&gt;</span></span><br><span class=\"line\"><span class=\"tag\">&lt;<span class=\"name\">package</span> <span class=\"attr\">format</span>=<span class=\"string\">&quot;3&quot;</span>&gt;</span></span><br><span class=\"line\">  <span class=\"comment\">&lt;!-- # 根据内容修改 --&gt;</span></span><br><span class=\"line\">  <span class=\"tag\">&lt;<span class=\"name\">name</span>&gt;</span>moveit_resources_panda_description<span class=\"tag\">&lt;/<span class=\"name\">name</span>&gt;</span> </span><br><span class=\"line\"></span><br><span class=\"line\">  <span class=\"tag\">&lt;<span class=\"name\">version</span>&gt;</span>2.0.6<span class=\"tag\">&lt;/<span class=\"name\">version</span>&gt;</span></span><br><span class=\"line\">  <span class=\"tag\">&lt;<span class=\"name\">description</span>&gt;</span>panda Resources used for MoveIt testing<span class=\"tag\">&lt;/<span class=\"name\">description</span>&gt;</span></span><br><span class=\"line\"></span><br><span class=\"line\">  <span class=\"tag\">&lt;<span class=\"name\">author</span> <span class=\"attr\">email</span>=<span class=\"string\">&quot;isucan@willowgarage.edu&quot;</span>&gt;</span>Ioan Sucan<span class=\"tag\">&lt;/<span class=\"name\">author</span>&gt;</span></span><br><span class=\"line\">  <span class=\"tag\">&lt;<span class=\"name\">author</span> <span class=\"attr\">email</span>=<span class=\"string\">&quot;acorn@willowgarage.edu&quot;</span>&gt;</span>Acorn Pooley<span class=\"tag\">&lt;/<span class=\"name\">author</span>&gt;</span></span><br><span class=\"line\"></span><br><span class=\"line\">  <span class=\"tag\">&lt;<span class=\"name\">maintainer</span> <span class=\"attr\">email</span>=<span class=\"string\">&quot;dave@dav.ee&quot;</span>&gt;</span>Dave Coleman<span class=\"tag\">&lt;/<span class=\"name\">maintainer</span>&gt;</span></span><br><span class=\"line\"></span><br><span class=\"line\">  <span class=\"tag\">&lt;<span class=\"name\">license</span>&gt;</span>BSD<span class=\"tag\">&lt;/<span class=\"name\">license</span>&gt;</span></span><br><span class=\"line\"></span><br><span class=\"line\">  <span class=\"tag\">&lt;<span class=\"name\">buildtool_depend</span>&gt;</span>ament_cmake<span class=\"tag\">&lt;/<span class=\"name\">buildtool_depend</span>&gt;</span></span><br><span class=\"line\"></span><br><span class=\"line\">  <span class=\"tag\">&lt;<span class=\"name\">export</span>&gt;</span></span><br><span class=\"line\">      <span class=\"tag\">&lt;<span class=\"name\">build_type</span>&gt;</span>ament_cmake<span class=\"tag\">&lt;/<span class=\"name\">build_type</span>&gt;</span></span><br><span class=\"line\">  <span class=\"tag\">&lt;/<span class=\"name\">export</span>&gt;</span></span><br><span class=\"line\"><span class=\"tag\">&lt;/<span class=\"name\">package</span>&gt;</span></span><br></pre></td></tr></table></figure>\n\n<h3 id=\"编译包\"><a href=\"#编译包\" class=\"headerlink\" title=\"编译包\"></a>编译包</h3><p>将包放入 ros2 或者 moveit2 工作空间中</p>\n<figure class=\"highlight bash\"><table><tr><td class=\"gutter\"><pre><span class=\"line\">1</span><br></pre></td><td class=\"code\"><pre><span class=\"line\">colcon build --packages-select moveit_resources_fanuc_description <span class=\"comment\"># 修改为自己的包名</span></span><br></pre></td></tr></table></figure>\n\n<h2 id=\"MoveIt-Setup-Assistant-配置\"><a href=\"#MoveIt-Setup-Assistant-配置\" class=\"headerlink\" title=\"MoveIt Setup Assistant 配置\"></a>MoveIt Setup Assistant 配置</h2><figure class=\"highlight bash\"><table><tr><td class=\"gutter\"><pre><span class=\"line\">1</span><br><span class=\"line\">2</span><br><span class=\"line\">3</span><br><span class=\"line\">4</span><br><span class=\"line\">5</span><br><span class=\"line\">6</span><br><span class=\"line\">7</span><br></pre></td><td class=\"code\"><pre><span class=\"line\"><span class=\"comment\"># 激活ros2环境</span></span><br><span class=\"line\"><span class=\"built_in\">source</span> /opt/ros/foxy/setup.bash</span><br><span class=\"line\"><span class=\"comment\"># 激活moveit环境</span></span><br><span class=\"line\"><span class=\"built_in\">source</span> ~/moveit2_ws/install/setup.bash <span class=\"comment\"># 刚才编译包的路径</span></span><br><span class=\"line\"><span class=\"comment\"># 启动moveit  MoveIt Setup Assistant</span></span><br><span class=\"line\">ros2 launch moveit_setup_assistant setup_assistant.launch.py</span><br><span class=\"line\"></span><br></pre></td></tr></table></figure>\n\n<p>剩下的就参照<a href=\"https://moveit.picknik.ai/main/doc/examples/setup_assistant/setup_assistant_tutorial.html\">官网文档</a></p>\n<h2 id=\"演示\"><a href=\"#演示\" class=\"headerlink\" title=\"演示\"></a>演示</h2><figure class=\"highlight bash\"><table><tr><td class=\"gutter\"><pre><span class=\"line\">1</span><br><span class=\"line\">2</span><br></pre></td><td class=\"code\"><pre><span class=\"line\"><span class=\"comment\"># 运行演示</span></span><br><span class=\"line\">ros2 launch panda_moveit_config demo.launch.py <span class=\"comment\"># 修改为自己的包名</span></span><br></pre></td></tr></table></figure>\n\n<p><img src=\"https://img.undf.top/image/ros2_urdf/%E8%BD%A8%E8%BF%B9%E8%A7%84%E5%88%92-2023-08-21.gif\" alt=\"轨迹规划-2023-08-21\"></p>\n<h2 id=\"其他\"><a href=\"#其他\" class=\"headerlink\" title=\"其他\"></a>其他</h2><p>我在导出复杂模型时遇到一些问题，可能是插件的问题，导出的模型有些问题，但是简单模型没有问题</p>\n<p>经过CoppeliaSim Edu导入再导出，可以解决这个问题（记得修改urdf内的文件路径）</p>\n","categories":[],"tags":[{"name":"ROS2","path":"api/tags/ROS2.json"}]}