{"name":"Embeded","postlist":[{"title":"address_calculate","slug":"code/address_calculate","date":"2022-10-21T06:20:49.000Z","updated":"2023-07-03T15:37:25.090Z","comments":true,"path":"api/articles/code/address_calculate.json","excerpt":null,"keywords":null,"cover":"https://img.undf.top/cundf/others/address_calculate.md/2022-10-21-14-24-44.png","content":null,"raw":null,"categories":[{"name":"Embeded","path":"api/categories/Embeded.json"}],"tags":[{"name":"Embeded","path":"api/tags/Embeded.json"}]}]}