{"title":"C++学习","slug":"code/C++学习","date":"2022-07-04T12:09:03.000Z","updated":"2022-08-08T06:27:52.312Z","comments":true,"path":"api/articles/code/C++学习.json","excerpt":null,"covers":["/images/others/2022-07-04-20-31-15.png","/images/others/2022-07-26-14-54-07.png","/images/others/C++PrimerPlus.md/2022-07-26-15-25-51.png","/images/others/2022-07-26-15-16-12.png","/images/others/C++PrimerPlus.md/2022-07-26-15-57-46.png","/images/others/C++PrimerPlus.md/2022-07-26-16-08-35.png","/images/others/C++PrimerPlus.md/2022-07-26-16-24-32.png","/images/others/C++%E5%AD%A6%E4%B9%A0.md/2022-08-02-15-13-43.png","/images/others/C++%E5%AD%A6%E4%B9%A0.md/2022-08-02-15-27-16.png","/images/others/C++%E5%AD%A6%E4%B9%A0.md/2022-08-02-15-28-43.png","/images/others/C++%E5%AD%A6%E4%B9%A0.md/2022-08-02-18-19-01.png","/images/others/C++%E5%AD%A6%E4%B9%A0.md/2022-08-02-18-40-41.png","/images/others/C++%E5%AD%A6%E4%B9%A0.md/2022-08-02-18-40-53.png","/images/others/C++%E5%AD%A6%E4%B9%A0.md/2022-08-02-18-49-53.png","/images/others/C++%E5%AD%A6%E4%B9%A0.md/2022-08-02-18-51-36.png","/images/others/C++%E5%AD%A6%E4%B9%A0.md/2022-08-03-14-11-51.png","/images/others/C++%E5%AD%A6%E4%B9%A0.md/2022-08-03-14-15-55.png","/images/others/C++%E5%AD%A6%E4%B9%A0.md/2022-08-03-14-18-52.png","/images/others/C++%E5%AD%A6%E4%B9%A0.md/2022-08-03-14-21-39.png","/images/others/C++%E5%AD%A6%E4%B9%A0.md/2022-08-03-14-24-41.png","/images/others/C++%E5%AD%A6%E4%B9%A0.md/2022-08-03-14-26-44.png","/images/others/C++%E5%AD%A6%E4%B9%A0.md/2022-08-04-12-00-36.png","/images/others/C++%E5%AD%A6%E4%B9%A0.md/2022-08-04-12-03-13.png","/images/others/C++%E5%AD%A6%E4%B9%A0.md/2022-08-05-15-03-03.png","/images/others/C++%E5%AD%A6%E4%B9%A0.md/2022-08-05-15-31-30.png","/images/others/C++%E5%AD%A6%E4%B9%A0.md/2022-08-05-15-31-32.png","/images/others/C++%E5%AD%A6%E4%B9%A0.md/2022-08-05-15-38-34.png","/images/others/C++%E5%AD%A6%E4%B9%A0.md/2022-08-05-15-39-49.png"],"content":"<h2 id=\"因\"><a href=\"#因\" class=\"headerlink\" title=\"因\"></a>因</h2><p>目前 c++的学习主要是针对三个方向</p>\n<ul>\n<li>基本语法</li>\n<li>数据结构</li>\n<li>QT(能用就行的地步)</li>\n</ul>\n<p>参考书:</p>\n<ul>\n<li>C++ Primer Plus（第 6 版）</li>\n<li>数据结构、算法与应用 C++语言描述原书第 2 版</li>\n<li>Qt 5.9 C++开发指南 (王维波 栗宝鹃 侯春望)</li>\n<li>Qt5 开发及实例（第 3 版） (陆文周)</li>\n</ul>\n<h2 id=\"基本语法\"><a href=\"#基本语法\" class=\"headerlink\" title=\"基本语法\"></a>基本语法</h2><h2 id=\"数据结构\"><a href=\"#数据结构\" class=\"headerlink\" title=\"数据结构\"></a>数据结构</h2><p>参照书前的学习计划安排自己的学习计划</p>\n<p><img src=\"/images/others/2022-07-04-20-31-15.png\"><br><img src=\"/images/others/2022-07-04-20-31-32.png\"><br>p31</p>\n<h2 id=\"QT\"><a href=\"#QT\" class=\"headerlink\" title=\"QT\"></a>QT</h2><h2 id=\"C-PrimerPlus\"><a href=\"#C-PrimerPlus\" class=\"headerlink\" title=\"C++ PrimerPlus\"></a>C++ PrimerPlus</h2><h3 id=\"第一章-预备知识\"><a href=\"#第一章-预备知识\" class=\"headerlink\" title=\"第一章 预备知识\"></a>第一章 预备知识</h3><p>一些原理，之前就已经学过，这里就不再详细记录。</p>\n<p><img src=\"/images/others/2022-07-26-14-54-07.png\" alt=\"2\"></p>\n<h3 id=\"第二章-开始学习\"><a href=\"#第二章-开始学习\" class=\"headerlink\" title=\"第二章 开始学习\"></a>第二章 开始学习</h3><p><img src=\"/images/others/C++PrimerPlus.md/2022-07-26-15-25-51.png\"></p>\n<p><img src=\"/images/others/2022-07-26-15-16-12.png\"></p>\n<p>基本也没太多知识点，简单记一个吧。</p>\n<p><img src=\"/images/others/C++PrimerPlus.md/2022-07-26-15-57-46.png\"></p>\n<figure class=\"highlight cpp\"><table><tr><td class=\"gutter\"><pre><span class=\"line\">1</span><br><span class=\"line\">2</span><br></pre></td><td class=\"code\"><pre><span class=\"line\"><span class=\"keyword\">using</span>  std::cout; <span class=\"comment\">// namespace</span></span><br><span class=\"line\"><span class=\"keyword\">using</span> <span class=\"keyword\">namespace</span> std; <span class=\"comment\">// namespace</span></span><br></pre></td></tr></table></figure>\n\n<h3 id=\"第三章-处理数据\"><a href=\"#第三章-处理数据\" class=\"headerlink\" title=\"第三章 处理数据\"></a>第三章 处理数据</h3><p><img src=\"/images/others/C++PrimerPlus.md/2022-07-26-16-08-35.png\"></p>\n<h4 id=\"c-11-初始化方式\"><a href=\"#c-11-初始化方式\" class=\"headerlink\" title=\"c++ 11 初始化方式\"></a>c++ 11 初始化方式</h4><p><img src=\"/images/others/C++PrimerPlus.md/2022-07-26-16-24-32.png\"></p>\n<p>这里第一次见，跑一下看看</p>\n<figure class=\"highlight cpp\"><table><tr><td class=\"gutter\"><pre><span class=\"line\">1</span><br><span class=\"line\">2</span><br><span class=\"line\">3</span><br><span class=\"line\">4</span><br><span class=\"line\">5</span><br><span class=\"line\">6</span><br><span class=\"line\">7</span><br><span class=\"line\">8</span><br><span class=\"line\">9</span><br><span class=\"line\">10</span><br><span class=\"line\">11</span><br><span class=\"line\">12</span><br><span class=\"line\">13</span><br><span class=\"line\">14</span><br></pre></td><td class=\"code\"><pre><span class=\"line\"><span class=\"keyword\">using</span> <span class=\"keyword\">namespace</span> std; <span class=\"comment\">// namespace</span></span><br><span class=\"line\"><span class=\"type\">int</span> aaa = &#123;<span class=\"number\">7</span>&#125;;</span><br><span class=\"line\"><span class=\"type\">int</span> bbb&#123;<span class=\"number\">7</span>&#125;;</span><br><span class=\"line\"><span class=\"type\">int</span> ccc = &#123;&#125;;</span><br><span class=\"line\"><span class=\"type\">int</span> ddd&#123;&#125;;</span><br><span class=\"line\"></span><br><span class=\"line\"></span><br><span class=\"line\">cout &lt;&lt; aaa &lt;&lt; bbb &lt;&lt; ccc &lt;&lt; ddd &lt;&lt; endl;</span><br><span class=\"line\">cout &lt;&lt; <span class=\"built_in\">sizeof</span>(aaa) &lt;&lt; <span class=\"built_in\">sizeof</span>(bbb) &lt;&lt; <span class=\"built_in\">sizeof</span>(ccc) &lt;&lt; <span class=\"built_in\">sizeof</span>(ddd)  &lt;&lt; endl;</span><br><span class=\"line\"></span><br><span class=\"line\"><span class=\"comment\">//result</span></span><br><span class=\"line\"><span class=\"number\">7700</span></span><br><span class=\"line\"><span class=\"number\">4444</span></span><br><span class=\"line\"></span><br></pre></td></tr></table></figure>\n\n<p>看来是印刷错误</p>\n<p><img src=\"/images/others/C++%E5%AD%A6%E4%B9%A0.md/2022-08-02-15-13-43.png\"></p>\n<h4 id=\"强制类型转换\"><a href=\"#强制类型转换\" class=\"headerlink\" title=\"强制类型转换\"></a>强制类型转换</h4><figure class=\"highlight cpp\"><table><tr><td class=\"gutter\"><pre><span class=\"line\">1</span><br><span class=\"line\">2</span><br></pre></td><td class=\"code\"><pre><span class=\"line\">(<span class=\"type\">int</span>)aaa;    <span class=\"comment\">// c</span></span><br><span class=\"line\"><span class=\"built_in\">int</span>(aaa);   <span class=\"comment\">// c++</span></span><br></pre></td></tr></table></figure>\n\n<h4 id=\"auto-声明\"><a href=\"#auto-声明\" class=\"headerlink\" title=\"auto 声明\"></a>auto 声明</h4><p>尽量少用</p>\n<p><img src=\"/images/others/C++%E5%AD%A6%E4%B9%A0.md/2022-08-02-15-27-16.png\"></p>\n<h3 id=\"复合类型\"><a href=\"#复合类型\" class=\"headerlink\" title=\"复合类型\"></a>复合类型</h3><p><img src=\"/images/others/C++%E5%AD%A6%E4%B9%A0.md/2022-08-02-15-28-43.png\"></p>\n<h4 id=\"数组\"><a href=\"#数组\" class=\"headerlink\" title=\"数组\"></a>数组</h4><h5 id=\"初始化规则\"><a href=\"#初始化规则\" class=\"headerlink\" title=\"初始化规则\"></a>初始化规则</h5><figure class=\"highlight cpp\"><table><tr><td class=\"gutter\"><pre><span class=\"line\">1</span><br><span class=\"line\">2</span><br><span class=\"line\">3</span><br><span class=\"line\">4</span><br></pre></td><td class=\"code\"><pre><span class=\"line\"><span class=\"type\">int</span> cards[<span class=\"number\">5</span>] = &#123;<span class=\"number\">1</span>, <span class=\"number\">2</span>, <span class=\"number\">3</span>, <span class=\"number\">4</span>, <span class=\"number\">5</span>&#125;;     <span class=\"comment\">//ok</span></span><br><span class=\"line\"><span class=\"type\">int</span> cards[<span class=\"number\">5</span>];                       <span class=\"comment\">//ok</span></span><br><span class=\"line\">cards[<span class=\"number\">5</span>] = &#123;<span class=\"number\">1</span>, <span class=\"number\">2</span>, <span class=\"number\">3</span>, <span class=\"number\">4</span>, <span class=\"number\">5</span>&#125;;         <span class=\"comment\">// error</span></span><br><span class=\"line\">cards = hands                       <span class=\"comment\">// error</span></span><br></pre></td></tr></table></figure>\n\n<h5 id=\"C-11-初始化规则\"><a href=\"#C-11-初始化规则\" class=\"headerlink\" title=\"C++11 初始化规则\"></a>C++11 初始化规则</h5><figure class=\"highlight cpp\"><table><tr><td class=\"gutter\"><pre><span class=\"line\">1</span><br><span class=\"line\">2</span><br></pre></td><td class=\"code\"><pre><span class=\"line\"><span class=\"type\">double</span> cards[<span class=\"number\">5</span>]  &#123;<span class=\"number\">1.1</span>, <span class=\"number\">2.2</span>, <span class=\"number\">3.3</span>, <span class=\"number\">4.4</span>, <span class=\"number\">5.5</span>&#125;;     <span class=\"comment\">//omit the space between = and &#123;</span></span><br><span class=\"line\"><span class=\"type\">int</span> counts[<span class=\"number\">5</span>] &#123;&#125;;     <span class=\"comment\">// there are no elements in the &#123;&#125;, so the elements are default initialized = 0</span></span><br></pre></td></tr></table></figure>\n\n\n<p><img src=\"/images/others/C++%E5%AD%A6%E4%B9%A0.md/2022-08-02-18-19-01.png\"></p>\n<h4 id=\"字符串\"><a href=\"#字符串\" class=\"headerlink\" title=\"字符串\"></a>字符串</h4><h5 id=\"c-style\"><a href=\"#c-style\" class=\"headerlink\" title=\"c- style\"></a>c- style</h5><p>书上写了一堆，总之就是不好用，所以有了新的</p>\n<h5 id=\"C-style\"><a href=\"#C-style\" class=\"headerlink\" title=\"C++ style\"></a>C++ style</h5><p><code>&quot;string&quot;</code></p>\n<p>字符串初始化与数组初始化类似，也可以省略 &#x3D; </p>\n<h4 id=\"结构体\"><a href=\"#结构体\" class=\"headerlink\" title=\"结构体\"></a>结构体</h4><p>初始化与数组初始化类似，也可以省略 &#x3D; ，不允许缩窄转换</p>\n<h4 id=\"共用体\"><a href=\"#共用体\" class=\"headerlink\" title=\"共用体\"></a>共用体</h4><figure class=\"highlight cpp\"><table><tr><td class=\"gutter\"><pre><span class=\"line\">1</span><br><span class=\"line\">2</span><br><span class=\"line\">3</span><br><span class=\"line\">4</span><br></pre></td><td class=\"code\"><pre><span class=\"line\"><span class=\"keyword\">union</span> &#123;</span><br><span class=\"line\">    <span class=\"type\">int</span> a;</span><br><span class=\"line\">    <span class=\"type\">double</span> b;</span><br><span class=\"line\">&#125;;</span><br></pre></td></tr></table></figure>\n\n<h4 id=\"枚举\"><a href=\"#枚举\" class=\"headerlink\" title=\"枚举\"></a>枚举</h4><figure class=\"highlight cpp\"><table><tr><td class=\"gutter\"><pre><span class=\"line\">1</span><br><span class=\"line\">2</span><br><span class=\"line\">3</span><br><span class=\"line\">4</span><br><span class=\"line\">5</span><br><span class=\"line\">6</span><br><span class=\"line\">7</span><br><span class=\"line\">8</span><br><span class=\"line\">9</span><br><span class=\"line\">10</span><br><span class=\"line\">11</span><br><span class=\"line\">12</span><br><span class=\"line\">13</span><br><span class=\"line\">14</span><br></pre></td><td class=\"code\"><pre><span class=\"line\"></span><br><span class=\"line\"><span class=\"keyword\">enum</span> <span class=\"title class_\">Color</span> &#123;</span><br><span class=\"line\">    RED,</span><br><span class=\"line\">    GREEN,</span><br><span class=\"line\">    BLUE</span><br><span class=\"line\">&#125;;</span><br><span class=\"line\"></span><br><span class=\"line\"></span><br><span class=\"line\"><span class=\"keyword\">enum</span> <span class=\"title class_\">Color</span> &#123;</span><br><span class=\"line\">    RED = <span class=\"number\">1</span>,</span><br><span class=\"line\">    GREEN = <span class=\"number\">2</span>,</span><br><span class=\"line\">    BLUE = <span class=\"number\">3</span></span><br><span class=\"line\">&#125;;</span><br><span class=\"line\"></span><br></pre></td></tr></table></figure>\n\n<h4 id=\"指针和自由存储空间\"><a href=\"#指针和自由存储空间\" class=\"headerlink\" title=\"指针和自由存储空间\"></a>指针和自由存储空间</h4><p><img src=\"/images/others/C++%E5%AD%A6%E4%B9%A0.md/2022-08-02-18-40-41.png\"></p>\n<p><img src=\"/images/others/C++%E5%AD%A6%E4%B9%A0.md/2022-08-02-18-40-53.png\"></p>\n<figure class=\"highlight cpp\"><table><tr><td class=\"gutter\"><pre><span class=\"line\">1</span><br><span class=\"line\">2</span><br><span class=\"line\">3</span><br><span class=\"line\">4</span><br><span class=\"line\">5</span><br><span class=\"line\">6</span><br></pre></td><td class=\"code\"><pre><span class=\"line\"><span class=\"type\">int</span> *p = <span class=\"keyword\">new</span> <span class=\"type\">int</span>;</span><br><span class=\"line\"><span class=\"keyword\">delete</span> p;</span><br><span class=\"line\"></span><br><span class=\"line\"><span class=\"type\">int</span> *p = <span class=\"keyword\">new</span> <span class=\"type\">int</span>[<span class=\"number\">10</span>];</span><br><span class=\"line\"><span class=\"keyword\">delete</span>[] p;   <span class=\"comment\">// [] 是告诉编译器，释放整个数组，而不是单个元素</span></span><br><span class=\"line\"></span><br></pre></td></tr></table></figure>\n\n<h4 id=\"vector\"><a href=\"#vector\" class=\"headerlink\" title=\"vector\"></a>vector</h4><figure class=\"highlight cpp\"><table><tr><td class=\"gutter\"><pre><span class=\"line\">1</span><br><span class=\"line\">2</span><br><span class=\"line\">3</span><br></pre></td><td class=\"code\"><pre><span class=\"line\"><span class=\"meta\"># <span class=\"keyword\">include</span> <span class=\"string\">&lt;vector&gt;</span></span></span><br><span class=\"line\">vector&lt;<span class=\"type\">int</span>&gt; v;</span><br><span class=\"line\">v.<span class=\"built_in\">push_back</span>(<span class=\"number\">1</span>);</span><br></pre></td></tr></table></figure>\n<h4 id=\"array\"><a href=\"#array\" class=\"headerlink\" title=\"array\"></a>array</h4><figure class=\"highlight cpp\"><table><tr><td class=\"gutter\"><pre><span class=\"line\">1</span><br><span class=\"line\">2</span><br></pre></td><td class=\"code\"><pre><span class=\"line\"><span class=\"meta\"># <span class=\"keyword\">include</span> <span class=\"string\">&lt;array&gt;</span></span></span><br><span class=\"line\">array&lt;<span class=\"type\">int</span>, 10&gt; a;</span><br></pre></td></tr></table></figure>\n\n<p><img src=\"/images/others/C++%E5%AD%A6%E4%B9%A0.md/2022-08-02-18-49-53.png\"></p>\n<h4 id=\"小结\"><a href=\"#小结\" class=\"headerlink\" title=\"小结\"></a>小结</h4><p><img src=\"/images/others/C++%E5%AD%A6%E4%B9%A0.md/2022-08-02-18-51-36.png\"></p>\n<h3 id=\"循环和关系表达式\"><a href=\"#循环和关系表达式\" class=\"headerlink\" title=\"循环和关系表达式\"></a>循环和关系表达式</h3><p><img src=\"/images/others/C++%E5%AD%A6%E4%B9%A0.md/2022-08-03-14-11-51.png\"></p>\n<p><img src=\"/images/others/C++%E5%AD%A6%E4%B9%A0.md/2022-08-03-14-15-55.png\"></p>\n<p><img src=\"/images/others/C++%E5%AD%A6%E4%B9%A0.md/2022-08-03-14-18-52.png\"></p>\n<p><img src=\"/images/others/C++%E5%AD%A6%E4%B9%A0.md/2022-08-03-14-21-39.png\"></p>\n<p>这个有点意思</p>\n<p><img src=\"/images/others/C++%E5%AD%A6%E4%B9%A0.md/2022-08-03-14-24-41.png\"></p>\n<h4 id=\"小结-1\"><a href=\"#小结-1\" class=\"headerlink\" title=\"小结\"></a>小结</h4><p><img src=\"/images/others/C++%E5%AD%A6%E4%B9%A0.md/2022-08-03-14-26-44.png\"></p>\n<h3 id=\"分支语句和逻辑运算符\"><a href=\"#分支语句和逻辑运算符\" class=\"headerlink\" title=\"分支语句和逻辑运算符\"></a>分支语句和逻辑运算符</h3><p><img src=\"/images/others/C++%E5%AD%A6%E4%B9%A0.md/2022-08-04-12-00-36.png\"></p>\n<h4 id=\"cctype\"><a href=\"#cctype\" class=\"headerlink\" title=\"cctype\"></a>cctype</h4><figure class=\"highlight cpp\"><table><tr><td class=\"gutter\"><pre><span class=\"line\">1</span><br><span class=\"line\">2</span><br><span class=\"line\">3</span><br><span class=\"line\">4</span><br><span class=\"line\">5</span><br><span class=\"line\">6</span><br><span class=\"line\">7</span><br><span class=\"line\">8</span><br></pre></td><td class=\"code\"><pre><span class=\"line\"><span class=\"meta\">#<span class=\"keyword\">include</span> <span class=\"string\">&lt;cctype&gt;</span></span></span><br><span class=\"line\"><span class=\"built_in\">isalpha</span>(<span class=\"string\">&#x27;a&#x27;</span>); <span class=\"comment\">// true</span></span><br><span class=\"line\"><span class=\"built_in\">isalpha</span>(<span class=\"string\">&#x27;1&#x27;</span>); <span class=\"comment\">// false</span></span><br><span class=\"line\"></span><br><span class=\"line\"><span class=\"built_in\">isupper</span>(<span class=\"string\">&#x27;A&#x27;</span>); <span class=\"comment\">// true</span></span><br><span class=\"line\"><span class=\"built_in\">isupper</span>(<span class=\"string\">&#x27;1&#x27;</span>); <span class=\"comment\">// false</span></span><br><span class=\"line\"></span><br><span class=\"line\"></span><br></pre></td></tr></table></figure>\n\n<p><img src=\"/images/others/C++%E5%AD%A6%E4%B9%A0.md/2022-08-04-12-03-13.png\"></p>\n<h4 id=\"简单文件输入输出\"><a href=\"#简单文件输入输出\" class=\"headerlink\" title=\"简单文件输入输出\"></a>简单文件输入输出</h4><figure class=\"highlight cpp\"><table><tr><td class=\"gutter\"><pre><span class=\"line\">1</span><br><span class=\"line\">2</span><br><span class=\"line\">3</span><br></pre></td><td class=\"code\"><pre><span class=\"line\"><span class=\"type\">char</span> word[<span class=\"number\">20</span>];</span><br><span class=\"line\">cin.<span class=\"built_in\">getline</span>(word, <span class=\"number\">20</span>);</span><br><span class=\"line\">cout &lt;&lt; word &lt;&lt; endl;</span><br></pre></td></tr></table></figure>\n<p>在这种情况下，c将不断读取，直到遇到换行符（示例输入行少于20个字符）。所有字符都将被存储到数组wod中，并在末尾加上一个空字符。换行符被丢弃，输入队列中的下一个字符是下一行中的第一个字符。这里不需要进行任何转换。</p>\n<h5 id=\"write\"><a href=\"#write\" class=\"headerlink\" title=\"write\"></a>write</h5><figure class=\"highlight cpp\"><table><tr><td class=\"gutter\"><pre><span class=\"line\">1</span><br><span class=\"line\">2</span><br><span class=\"line\">3</span><br><span class=\"line\">4</span><br><span class=\"line\">5</span><br><span class=\"line\">6</span><br><span class=\"line\">7</span><br></pre></td><td class=\"code\"><pre><span class=\"line\">ofstream out;</span><br><span class=\"line\">out.<span class=\"built_in\">open</span>(<span class=\"string\">&quot;test.txt&quot;</span>); </span><br><span class=\"line\"><span class=\"comment\">//ofstream out(&quot;test.txt&quot;);</span></span><br><span class=\"line\"></span><br><span class=\"line\">out &lt;&lt; <span class=\"string\">&quot;Hello, world!&quot;</span> &lt;&lt; endl;</span><br><span class=\"line\"></span><br><span class=\"line\">out.<span class=\"built_in\">close</span>();</span><br></pre></td></tr></table></figure>\n<h5 id=\"read\"><a href=\"#read\" class=\"headerlink\" title=\"read\"></a>read</h5><figure class=\"highlight cpp\"><table><tr><td class=\"gutter\"><pre><span class=\"line\">1</span><br><span class=\"line\">2</span><br><span class=\"line\">3</span><br><span class=\"line\">4</span><br><span class=\"line\">5</span><br><span class=\"line\">6</span><br><span class=\"line\">7</span><br></pre></td><td class=\"code\"><pre><span class=\"line\">ifstream in;</span><br><span class=\"line\"><span class=\"type\">char</span> word[<span class=\"number\">20</span>];</span><br><span class=\"line\">in.<span class=\"built_in\">open</span>(<span class=\"string\">&quot;test.txt&quot;</span>);</span><br><span class=\"line\">in &gt;&gt; word;</span><br><span class=\"line\">cout &lt;&lt; word &lt;&lt; endl;</span><br><span class=\"line\"></span><br><span class=\"line\">in.<span class=\"built_in\">close</span>();</span><br></pre></td></tr></table></figure>\n\n<p>不得不说python和c++好像啊.</p>\n<h3 id=\"函数\"><a href=\"#函数\" class=\"headerlink\" title=\"函数\"></a>函数</h3><p><img src=\"/images/others/C++%E5%AD%A6%E4%B9%A0.md/2022-08-05-15-03-03.png\"></p>\n<p>const</p>\n<p><img src=\"/images/others/C++%E5%AD%A6%E4%B9%A0.md/2022-08-05-15-31-30.png\"></p>\n<p><img src=\"/images/others/C++%E5%AD%A6%E4%B9%A0.md/2022-08-05-15-31-32.png\"></p>\n<h4 id=\"函数指针\"><a href=\"#函数指针\" class=\"headerlink\" title=\"函数指针\"></a>函数指针</h4><figure class=\"highlight cpp\"><table><tr><td class=\"gutter\"><pre><span class=\"line\">1</span><br><span class=\"line\">2</span><br><span class=\"line\">3</span><br><span class=\"line\">4</span><br><span class=\"line\">5</span><br><span class=\"line\">6</span><br><span class=\"line\">7</span><br></pre></td><td class=\"code\"><pre><span class=\"line\"><span class=\"function\"><span class=\"type\">int</span> <span class=\"title\">add</span><span class=\"params\">(<span class=\"type\">int</span> a, <span class=\"type\">int</span> b)</span> </span>&#123;</span><br><span class=\"line\">    <span class=\"keyword\">return</span> a + b;</span><br><span class=\"line\">&#125;</span><br><span class=\"line\"><span class=\"built_in\">int</span> (*p)(<span class=\"type\">int</span> a, <span class=\"type\">int</span> b);</span><br><span class=\"line\">p = add;</span><br><span class=\"line\"><span class=\"built_in\">p</span>(<span class=\"number\">1</span>, <span class=\"number\">2</span>);</span><br><span class=\"line\"></span><br></pre></td></tr></table></figure>\n<h4 id=\"小结-2\"><a href=\"#小结-2\" class=\"headerlink\" title=\"小结\"></a>小结</h4><p><img src=\"/images/others/C++%E5%AD%A6%E4%B9%A0.md/2022-08-05-15-38-34.png\"></p>\n<p><img src=\"/images/others/C++%E5%AD%A6%E4%B9%A0.md/2022-08-05-15-39-49.png\"></p>\n<link rel=\"stylesheet\" href=\"/css/spoiler.css\" type=\"text/css\"><script src=\"/js/spoiler.js\" type=\"text/javascript\" async></script>","more":"<h2 id=\"因\"><a href=\"#因\" class=\"headerlink\" title=\"因\"></a>因</h2><p>目前 c++的学习主要是针对三个方向</p>\n<ul>\n<li>基本语法</li>\n<li>数据结构</li>\n<li>QT(能用就行的地步)</li>\n</ul>\n<p>参考书:</p>\n<ul>\n<li>C++ Primer Plus（第 6 版）</li>\n<li>数据结构、算法与应用 C++语言描述原书第 2 版</li>\n<li>Qt 5.9 C++开发指南 (王维波 栗宝鹃 侯春望)</li>\n<li>Qt5 开发及实例（第 3 版） (陆文周)</li>\n</ul>\n<h2 id=\"基本语法\"><a href=\"#基本语法\" class=\"headerlink\" title=\"基本语法\"></a>基本语法</h2><h2 id=\"数据结构\"><a href=\"#数据结构\" class=\"headerlink\" title=\"数据结构\"></a>数据结构</h2><p>参照书前的学习计划安排自己的学习计划</p>\n<p><img src=\"/images/others/2022-07-04-20-31-15.png\"><br><img src=\"/images/others/2022-07-04-20-31-32.png\"><br>p31</p>\n<h2 id=\"QT\"><a href=\"#QT\" class=\"headerlink\" title=\"QT\"></a>QT</h2><h2 id=\"C-PrimerPlus\"><a href=\"#C-PrimerPlus\" class=\"headerlink\" title=\"C++ PrimerPlus\"></a>C++ PrimerPlus</h2><h3 id=\"第一章-预备知识\"><a href=\"#第一章-预备知识\" class=\"headerlink\" title=\"第一章 预备知识\"></a>第一章 预备知识</h3><p>一些原理，之前就已经学过，这里就不再详细记录。</p>\n<p><img src=\"/images/others/2022-07-26-14-54-07.png\" alt=\"2\"></p>\n<h3 id=\"第二章-开始学习\"><a href=\"#第二章-开始学习\" class=\"headerlink\" title=\"第二章 开始学习\"></a>第二章 开始学习</h3><p><img src=\"/images/others/C++PrimerPlus.md/2022-07-26-15-25-51.png\"></p>\n<p><img src=\"/images/others/2022-07-26-15-16-12.png\"></p>\n<p>基本也没太多知识点，简单记一个吧。</p>\n<p><img src=\"/images/others/C++PrimerPlus.md/2022-07-26-15-57-46.png\"></p>\n<figure class=\"highlight cpp\"><table><tr><td class=\"gutter\"><pre><span class=\"line\">1</span><br><span class=\"line\">2</span><br></pre></td><td class=\"code\"><pre><span class=\"line\"><span class=\"keyword\">using</span>  std::cout; <span class=\"comment\">// namespace</span></span><br><span class=\"line\"><span class=\"keyword\">using</span> <span class=\"keyword\">namespace</span> std; <span class=\"comment\">// namespace</span></span><br></pre></td></tr></table></figure>\n\n<h3 id=\"第三章-处理数据\"><a href=\"#第三章-处理数据\" class=\"headerlink\" title=\"第三章 处理数据\"></a>第三章 处理数据</h3><p><img src=\"/images/others/C++PrimerPlus.md/2022-07-26-16-08-35.png\"></p>\n<h4 id=\"c-11-初始化方式\"><a href=\"#c-11-初始化方式\" class=\"headerlink\" title=\"c++ 11 初始化方式\"></a>c++ 11 初始化方式</h4><p><img src=\"/images/others/C++PrimerPlus.md/2022-07-26-16-24-32.png\"></p>\n<p>这里第一次见，跑一下看看</p>\n<figure class=\"highlight cpp\"><table><tr><td class=\"gutter\"><pre><span class=\"line\">1</span><br><span class=\"line\">2</span><br><span class=\"line\">3</span><br><span class=\"line\">4</span><br><span class=\"line\">5</span><br><span class=\"line\">6</span><br><span class=\"line\">7</span><br><span class=\"line\">8</span><br><span class=\"line\">9</span><br><span class=\"line\">10</span><br><span class=\"line\">11</span><br><span class=\"line\">12</span><br><span class=\"line\">13</span><br><span class=\"line\">14</span><br></pre></td><td class=\"code\"><pre><span class=\"line\"><span class=\"keyword\">using</span> <span class=\"keyword\">namespace</span> std; <span class=\"comment\">// namespace</span></span><br><span class=\"line\"><span class=\"type\">int</span> aaa = &#123;<span class=\"number\">7</span>&#125;;</span><br><span class=\"line\"><span class=\"type\">int</span> bbb&#123;<span class=\"number\">7</span>&#125;;</span><br><span class=\"line\"><span class=\"type\">int</span> ccc = &#123;&#125;;</span><br><span class=\"line\"><span class=\"type\">int</span> ddd&#123;&#125;;</span><br><span class=\"line\"></span><br><span class=\"line\"></span><br><span class=\"line\">cout &lt;&lt; aaa &lt;&lt; bbb &lt;&lt; ccc &lt;&lt; ddd &lt;&lt; endl;</span><br><span class=\"line\">cout &lt;&lt; <span class=\"built_in\">sizeof</span>(aaa) &lt;&lt; <span class=\"built_in\">sizeof</span>(bbb) &lt;&lt; <span class=\"built_in\">sizeof</span>(ccc) &lt;&lt; <span class=\"built_in\">sizeof</span>(ddd)  &lt;&lt; endl;</span><br><span class=\"line\"></span><br><span class=\"line\"><span class=\"comment\">//result</span></span><br><span class=\"line\"><span class=\"number\">7700</span></span><br><span class=\"line\"><span class=\"number\">4444</span></span><br><span class=\"line\"></span><br></pre></td></tr></table></figure>\n\n<p>看来是印刷错误</p>\n<p><img src=\"/images/others/C++%E5%AD%A6%E4%B9%A0.md/2022-08-02-15-13-43.png\"></p>\n<h4 id=\"强制类型转换\"><a href=\"#强制类型转换\" class=\"headerlink\" title=\"强制类型转换\"></a>强制类型转换</h4><figure class=\"highlight cpp\"><table><tr><td class=\"gutter\"><pre><span class=\"line\">1</span><br><span class=\"line\">2</span><br></pre></td><td class=\"code\"><pre><span class=\"line\">(<span class=\"type\">int</span>)aaa;    <span class=\"comment\">// c</span></span><br><span class=\"line\"><span class=\"built_in\">int</span>(aaa);   <span class=\"comment\">// c++</span></span><br></pre></td></tr></table></figure>\n\n<h4 id=\"auto-声明\"><a href=\"#auto-声明\" class=\"headerlink\" title=\"auto 声明\"></a>auto 声明</h4><p>尽量少用</p>\n<p><img src=\"/images/others/C++%E5%AD%A6%E4%B9%A0.md/2022-08-02-15-27-16.png\"></p>\n<h3 id=\"复合类型\"><a href=\"#复合类型\" class=\"headerlink\" title=\"复合类型\"></a>复合类型</h3><p><img src=\"/images/others/C++%E5%AD%A6%E4%B9%A0.md/2022-08-02-15-28-43.png\"></p>\n<h4 id=\"数组\"><a href=\"#数组\" class=\"headerlink\" title=\"数组\"></a>数组</h4><h5 id=\"初始化规则\"><a href=\"#初始化规则\" class=\"headerlink\" title=\"初始化规则\"></a>初始化规则</h5><figure class=\"highlight cpp\"><table><tr><td class=\"gutter\"><pre><span class=\"line\">1</span><br><span class=\"line\">2</span><br><span class=\"line\">3</span><br><span class=\"line\">4</span><br></pre></td><td class=\"code\"><pre><span class=\"line\"><span class=\"type\">int</span> cards[<span class=\"number\">5</span>] = &#123;<span class=\"number\">1</span>, <span class=\"number\">2</span>, <span class=\"number\">3</span>, <span class=\"number\">4</span>, <span class=\"number\">5</span>&#125;;     <span class=\"comment\">//ok</span></span><br><span class=\"line\"><span class=\"type\">int</span> cards[<span class=\"number\">5</span>];                       <span class=\"comment\">//ok</span></span><br><span class=\"line\">cards[<span class=\"number\">5</span>] = &#123;<span class=\"number\">1</span>, <span class=\"number\">2</span>, <span class=\"number\">3</span>, <span class=\"number\">4</span>, <span class=\"number\">5</span>&#125;;         <span class=\"comment\">// error</span></span><br><span class=\"line\">cards = hands                       <span class=\"comment\">// error</span></span><br></pre></td></tr></table></figure>\n\n<h5 id=\"C-11-初始化规则\"><a href=\"#C-11-初始化规则\" class=\"headerlink\" title=\"C++11 初始化规则\"></a>C++11 初始化规则</h5><figure class=\"highlight cpp\"><table><tr><td class=\"gutter\"><pre><span class=\"line\">1</span><br><span class=\"line\">2</span><br></pre></td><td class=\"code\"><pre><span class=\"line\"><span class=\"type\">double</span> cards[<span class=\"number\">5</span>]  &#123;<span class=\"number\">1.1</span>, <span class=\"number\">2.2</span>, <span class=\"number\">3.3</span>, <span class=\"number\">4.4</span>, <span class=\"number\">5.5</span>&#125;;     <span class=\"comment\">//omit the space between = and &#123;</span></span><br><span class=\"line\"><span class=\"type\">int</span> counts[<span class=\"number\">5</span>] &#123;&#125;;     <span class=\"comment\">// there are no elements in the &#123;&#125;, so the elements are default initialized = 0</span></span><br></pre></td></tr></table></figure>\n\n\n<p><img src=\"/images/others/C++%E5%AD%A6%E4%B9%A0.md/2022-08-02-18-19-01.png\"></p>\n<h4 id=\"字符串\"><a href=\"#字符串\" class=\"headerlink\" title=\"字符串\"></a>字符串</h4><h5 id=\"c-style\"><a href=\"#c-style\" class=\"headerlink\" title=\"c- style\"></a>c- style</h5><p>书上写了一堆，总之就是不好用，所以有了新的</p>\n<h5 id=\"C-style\"><a href=\"#C-style\" class=\"headerlink\" title=\"C++ style\"></a>C++ style</h5><p><code>&quot;string&quot;</code></p>\n<p>字符串初始化与数组初始化类似，也可以省略 &#x3D; </p>\n<h4 id=\"结构体\"><a href=\"#结构体\" class=\"headerlink\" title=\"结构体\"></a>结构体</h4><p>初始化与数组初始化类似，也可以省略 &#x3D; ，不允许缩窄转换</p>\n<h4 id=\"共用体\"><a href=\"#共用体\" class=\"headerlink\" title=\"共用体\"></a>共用体</h4><figure class=\"highlight cpp\"><table><tr><td class=\"gutter\"><pre><span class=\"line\">1</span><br><span class=\"line\">2</span><br><span class=\"line\">3</span><br><span class=\"line\">4</span><br></pre></td><td class=\"code\"><pre><span class=\"line\"><span class=\"keyword\">union</span> &#123;</span><br><span class=\"line\">    <span class=\"type\">int</span> a;</span><br><span class=\"line\">    <span class=\"type\">double</span> b;</span><br><span class=\"line\">&#125;;</span><br></pre></td></tr></table></figure>\n\n<h4 id=\"枚举\"><a href=\"#枚举\" class=\"headerlink\" title=\"枚举\"></a>枚举</h4><figure class=\"highlight cpp\"><table><tr><td class=\"gutter\"><pre><span class=\"line\">1</span><br><span class=\"line\">2</span><br><span class=\"line\">3</span><br><span class=\"line\">4</span><br><span class=\"line\">5</span><br><span class=\"line\">6</span><br><span class=\"line\">7</span><br><span class=\"line\">8</span><br><span class=\"line\">9</span><br><span class=\"line\">10</span><br><span class=\"line\">11</span><br><span class=\"line\">12</span><br><span class=\"line\">13</span><br><span class=\"line\">14</span><br></pre></td><td class=\"code\"><pre><span class=\"line\"></span><br><span class=\"line\"><span class=\"keyword\">enum</span> <span class=\"title class_\">Color</span> &#123;</span><br><span class=\"line\">    RED,</span><br><span class=\"line\">    GREEN,</span><br><span class=\"line\">    BLUE</span><br><span class=\"line\">&#125;;</span><br><span class=\"line\"></span><br><span class=\"line\"></span><br><span class=\"line\"><span class=\"keyword\">enum</span> <span class=\"title class_\">Color</span> &#123;</span><br><span class=\"line\">    RED = <span class=\"number\">1</span>,</span><br><span class=\"line\">    GREEN = <span class=\"number\">2</span>,</span><br><span class=\"line\">    BLUE = <span class=\"number\">3</span></span><br><span class=\"line\">&#125;;</span><br><span class=\"line\"></span><br></pre></td></tr></table></figure>\n\n<h4 id=\"指针和自由存储空间\"><a href=\"#指针和自由存储空间\" class=\"headerlink\" title=\"指针和自由存储空间\"></a>指针和自由存储空间</h4><p><img src=\"/images/others/C++%E5%AD%A6%E4%B9%A0.md/2022-08-02-18-40-41.png\"></p>\n<p><img src=\"/images/others/C++%E5%AD%A6%E4%B9%A0.md/2022-08-02-18-40-53.png\"></p>\n<figure class=\"highlight cpp\"><table><tr><td class=\"gutter\"><pre><span class=\"line\">1</span><br><span class=\"line\">2</span><br><span class=\"line\">3</span><br><span class=\"line\">4</span><br><span class=\"line\">5</span><br><span class=\"line\">6</span><br></pre></td><td class=\"code\"><pre><span class=\"line\"><span class=\"type\">int</span> *p = <span class=\"keyword\">new</span> <span class=\"type\">int</span>;</span><br><span class=\"line\"><span class=\"keyword\">delete</span> p;</span><br><span class=\"line\"></span><br><span class=\"line\"><span class=\"type\">int</span> *p = <span class=\"keyword\">new</span> <span class=\"type\">int</span>[<span class=\"number\">10</span>];</span><br><span class=\"line\"><span class=\"keyword\">delete</span>[] p;   <span class=\"comment\">// [] 是告诉编译器，释放整个数组，而不是单个元素</span></span><br><span class=\"line\"></span><br></pre></td></tr></table></figure>\n\n<h4 id=\"vector\"><a href=\"#vector\" class=\"headerlink\" title=\"vector\"></a>vector</h4><figure class=\"highlight cpp\"><table><tr><td class=\"gutter\"><pre><span class=\"line\">1</span><br><span class=\"line\">2</span><br><span class=\"line\">3</span><br></pre></td><td class=\"code\"><pre><span class=\"line\"><span class=\"meta\"># <span class=\"keyword\">include</span> <span class=\"string\">&lt;vector&gt;</span></span></span><br><span class=\"line\">vector&lt;<span class=\"type\">int</span>&gt; v;</span><br><span class=\"line\">v.<span class=\"built_in\">push_back</span>(<span class=\"number\">1</span>);</span><br></pre></td></tr></table></figure>\n<h4 id=\"array\"><a href=\"#array\" class=\"headerlink\" title=\"array\"></a>array</h4><figure class=\"highlight cpp\"><table><tr><td class=\"gutter\"><pre><span class=\"line\">1</span><br><span class=\"line\">2</span><br></pre></td><td class=\"code\"><pre><span class=\"line\"><span class=\"meta\"># <span class=\"keyword\">include</span> <span class=\"string\">&lt;array&gt;</span></span></span><br><span class=\"line\">array&lt;<span class=\"type\">int</span>, 10&gt; a;</span><br></pre></td></tr></table></figure>\n\n<p><img src=\"/images/others/C++%E5%AD%A6%E4%B9%A0.md/2022-08-02-18-49-53.png\"></p>\n<h4 id=\"小结\"><a href=\"#小结\" class=\"headerlink\" title=\"小结\"></a>小结</h4><p><img src=\"/images/others/C++%E5%AD%A6%E4%B9%A0.md/2022-08-02-18-51-36.png\"></p>\n<h3 id=\"循环和关系表达式\"><a href=\"#循环和关系表达式\" class=\"headerlink\" title=\"循环和关系表达式\"></a>循环和关系表达式</h3><p><img src=\"/images/others/C++%E5%AD%A6%E4%B9%A0.md/2022-08-03-14-11-51.png\"></p>\n<p><img src=\"/images/others/C++%E5%AD%A6%E4%B9%A0.md/2022-08-03-14-15-55.png\"></p>\n<p><img src=\"/images/others/C++%E5%AD%A6%E4%B9%A0.md/2022-08-03-14-18-52.png\"></p>\n<p><img src=\"/images/others/C++%E5%AD%A6%E4%B9%A0.md/2022-08-03-14-21-39.png\"></p>\n<p>这个有点意思</p>\n<p><img src=\"/images/others/C++%E5%AD%A6%E4%B9%A0.md/2022-08-03-14-24-41.png\"></p>\n<h4 id=\"小结-1\"><a href=\"#小结-1\" class=\"headerlink\" title=\"小结\"></a>小结</h4><p><img src=\"/images/others/C++%E5%AD%A6%E4%B9%A0.md/2022-08-03-14-26-44.png\"></p>\n<h3 id=\"分支语句和逻辑运算符\"><a href=\"#分支语句和逻辑运算符\" class=\"headerlink\" title=\"分支语句和逻辑运算符\"></a>分支语句和逻辑运算符</h3><p><img src=\"/images/others/C++%E5%AD%A6%E4%B9%A0.md/2022-08-04-12-00-36.png\"></p>\n<h4 id=\"cctype\"><a href=\"#cctype\" class=\"headerlink\" title=\"cctype\"></a>cctype</h4><figure class=\"highlight cpp\"><table><tr><td class=\"gutter\"><pre><span class=\"line\">1</span><br><span class=\"line\">2</span><br><span class=\"line\">3</span><br><span class=\"line\">4</span><br><span class=\"line\">5</span><br><span class=\"line\">6</span><br><span class=\"line\">7</span><br><span class=\"line\">8</span><br></pre></td><td class=\"code\"><pre><span class=\"line\"><span class=\"meta\">#<span class=\"keyword\">include</span> <span class=\"string\">&lt;cctype&gt;</span></span></span><br><span class=\"line\"><span class=\"built_in\">isalpha</span>(<span class=\"string\">&#x27;a&#x27;</span>); <span class=\"comment\">// true</span></span><br><span class=\"line\"><span class=\"built_in\">isalpha</span>(<span class=\"string\">&#x27;1&#x27;</span>); <span class=\"comment\">// false</span></span><br><span class=\"line\"></span><br><span class=\"line\"><span class=\"built_in\">isupper</span>(<span class=\"string\">&#x27;A&#x27;</span>); <span class=\"comment\">// true</span></span><br><span class=\"line\"><span class=\"built_in\">isupper</span>(<span class=\"string\">&#x27;1&#x27;</span>); <span class=\"comment\">// false</span></span><br><span class=\"line\"></span><br><span class=\"line\"></span><br></pre></td></tr></table></figure>\n\n<p><img src=\"/images/others/C++%E5%AD%A6%E4%B9%A0.md/2022-08-04-12-03-13.png\"></p>\n<h4 id=\"简单文件输入输出\"><a href=\"#简单文件输入输出\" class=\"headerlink\" title=\"简单文件输入输出\"></a>简单文件输入输出</h4><figure class=\"highlight cpp\"><table><tr><td class=\"gutter\"><pre><span class=\"line\">1</span><br><span class=\"line\">2</span><br><span class=\"line\">3</span><br></pre></td><td class=\"code\"><pre><span class=\"line\"><span class=\"type\">char</span> word[<span class=\"number\">20</span>];</span><br><span class=\"line\">cin.<span class=\"built_in\">getline</span>(word, <span class=\"number\">20</span>);</span><br><span class=\"line\">cout &lt;&lt; word &lt;&lt; endl;</span><br></pre></td></tr></table></figure>\n<p>在这种情况下，c将不断读取，直到遇到换行符（示例输入行少于20个字符）。所有字符都将被存储到数组wod中，并在末尾加上一个空字符。换行符被丢弃，输入队列中的下一个字符是下一行中的第一个字符。这里不需要进行任何转换。</p>\n<h5 id=\"write\"><a href=\"#write\" class=\"headerlink\" title=\"write\"></a>write</h5><figure class=\"highlight cpp\"><table><tr><td class=\"gutter\"><pre><span class=\"line\">1</span><br><span class=\"line\">2</span><br><span class=\"line\">3</span><br><span class=\"line\">4</span><br><span class=\"line\">5</span><br><span class=\"line\">6</span><br><span class=\"line\">7</span><br></pre></td><td class=\"code\"><pre><span class=\"line\">ofstream out;</span><br><span class=\"line\">out.<span class=\"built_in\">open</span>(<span class=\"string\">&quot;test.txt&quot;</span>); </span><br><span class=\"line\"><span class=\"comment\">//ofstream out(&quot;test.txt&quot;);</span></span><br><span class=\"line\"></span><br><span class=\"line\">out &lt;&lt; <span class=\"string\">&quot;Hello, world!&quot;</span> &lt;&lt; endl;</span><br><span class=\"line\"></span><br><span class=\"line\">out.<span class=\"built_in\">close</span>();</span><br></pre></td></tr></table></figure>\n<h5 id=\"read\"><a href=\"#read\" class=\"headerlink\" title=\"read\"></a>read</h5><figure class=\"highlight cpp\"><table><tr><td class=\"gutter\"><pre><span class=\"line\">1</span><br><span class=\"line\">2</span><br><span class=\"line\">3</span><br><span class=\"line\">4</span><br><span class=\"line\">5</span><br><span class=\"line\">6</span><br><span class=\"line\">7</span><br></pre></td><td class=\"code\"><pre><span class=\"line\">ifstream in;</span><br><span class=\"line\"><span class=\"type\">char</span> word[<span class=\"number\">20</span>];</span><br><span class=\"line\">in.<span class=\"built_in\">open</span>(<span class=\"string\">&quot;test.txt&quot;</span>);</span><br><span class=\"line\">in &gt;&gt; word;</span><br><span class=\"line\">cout &lt;&lt; word &lt;&lt; endl;</span><br><span class=\"line\"></span><br><span class=\"line\">in.<span class=\"built_in\">close</span>();</span><br></pre></td></tr></table></figure>\n\n<p>不得不说python和c++好像啊.</p>\n<h3 id=\"函数\"><a href=\"#函数\" class=\"headerlink\" title=\"函数\"></a>函数</h3><p><img src=\"/images/others/C++%E5%AD%A6%E4%B9%A0.md/2022-08-05-15-03-03.png\"></p>\n<p>const</p>\n<p><img src=\"/images/others/C++%E5%AD%A6%E4%B9%A0.md/2022-08-05-15-31-30.png\"></p>\n<p><img src=\"/images/others/C++%E5%AD%A6%E4%B9%A0.md/2022-08-05-15-31-32.png\"></p>\n<h4 id=\"函数指针\"><a href=\"#函数指针\" class=\"headerlink\" title=\"函数指针\"></a>函数指针</h4><figure class=\"highlight cpp\"><table><tr><td class=\"gutter\"><pre><span class=\"line\">1</span><br><span class=\"line\">2</span><br><span class=\"line\">3</span><br><span class=\"line\">4</span><br><span class=\"line\">5</span><br><span class=\"line\">6</span><br><span class=\"line\">7</span><br></pre></td><td class=\"code\"><pre><span class=\"line\"><span class=\"function\"><span class=\"type\">int</span> <span class=\"title\">add</span><span class=\"params\">(<span class=\"type\">int</span> a, <span class=\"type\">int</span> b)</span> </span>&#123;</span><br><span class=\"line\">    <span class=\"keyword\">return</span> a + b;</span><br><span class=\"line\">&#125;</span><br><span class=\"line\"><span class=\"built_in\">int</span> (*p)(<span class=\"type\">int</span> a, <span class=\"type\">int</span> b);</span><br><span class=\"line\">p = add;</span><br><span class=\"line\"><span class=\"built_in\">p</span>(<span class=\"number\">1</span>, <span class=\"number\">2</span>);</span><br><span class=\"line\"></span><br></pre></td></tr></table></figure>\n<h4 id=\"小结-2\"><a href=\"#小结-2\" class=\"headerlink\" title=\"小结\"></a>小结</h4><p><img src=\"/images/others/C++%E5%AD%A6%E4%B9%A0.md/2022-08-05-15-38-34.png\"></p>\n<p><img src=\"/images/others/C++%E5%AD%A6%E4%B9%A0.md/2022-08-05-15-39-49.png\"></p>\n","categories":[],"tags":[{"name":"C++","path":"api/tags/C++.json"}]}