{"title":"ESP32","slug":"code/ESP32","date":"2022-06-10T04:23:15.000Z","updated":"2023-06-17T15:34:16.426Z","comments":true,"path":"api/articles/code/ESP32.json","excerpt":null,"covers":["https://image.wxydejoy.top/image/ESP32/20220610123118-2022-06-10.png","https://image.wxydejoy.top/image/ESP32/20220610123407-2022-06-10.png"],"content":"<h2 id=\"初\"><a href=\"#初\" class=\"headerlink\" title=\"初\"></a>初</h2><p>芯片涨价、支持国产、物联网、方便好用、支持低代码</p>\n<p>这些都是选择ESP32的原因之一</p>\n<h2 id=\"使用方法\"><a href=\"#使用方法\" class=\"headerlink\" title=\"使用方法\"></a>使用方法</h2><h3 id=\"AT指令\"><a href=\"#AT指令\" class=\"headerlink\" title=\"AT指令\"></a>AT指令</h3><p>可以使用简单的AT指令实现一些比较常用的功能</p>\n<p><img src=\"https://image.wxydejoy.top/image/ESP32/20220610123118-2022-06-10.png\" alt=\"20220610123118-2022-06-10\"></p>\n<p>这里丢个链接<a href=\"https://docs.espressif.com/projects/esp-at/zh_CN/latest/esp32/AT_Binary_Lists/index.html\">AT 固件 - ESP32 -  — ESP-AT 用户指南 latest 文档</a></p>\n<h3 id=\"C-x2F-C-语言编程\"><a href=\"#C-x2F-C-语言编程\" class=\"headerlink\" title=\"C&#x2F;C++语言编程\"></a>C&#x2F;C++语言编程</h3><ol>\n<li>VScode</li>\n</ol>\n<p>不建议小白使用，网上例程少，上手慢。</p>\n<p>初次编译慢，但后续修改方便，配合上vscode的错误提示，还可。</p>\n<p>这个是我目前在用的，因为AT指令不能完全满足我的需求，所以只能自己敲代码了。</p>\n<p>当然你也可以选择arduino，不过我觉得它又丑又慢，而且我本身经常用vscode。</p>\n<p>通过官方插件，日常使用还是很不错的。</p>\n<p><img src=\"https://image.wxydejoy.top/image/ESP32/20220610123407-2022-06-10.png\" alt=\"20220610123407-2022-06-10\"></p>\n<ol>\n<li>Arduino</li>\n</ol>\n<p>每次修改都要完全重新编译。</p>\n<p>又丑又慢，不过胜在编程操作简单。</p>\n<p>而且网上有很多例程，可以借鉴，开发效率稍微高点，建议新手使用。</p>\n<h2 id=\"一些问题\"><a href=\"#一些问题\" class=\"headerlink\" title=\"一些问题\"></a>一些问题</h2><ol>\n<li>不建议使用esp32的ADC接口，精度较低。</li>\n<li>AT指令无法调试PWM，暂未找到解决办法。</li>\n<li>ESP32资源有限，只能用在小项目或者副芯片。</li>\n</ol>\n","more":"<h2 id=\"初\"><a href=\"#初\" class=\"headerlink\" title=\"初\"></a>初</h2><p>芯片涨价、支持国产、物联网、方便好用、支持低代码</p>\n<p>这些都是选择ESP32的原因之一</p>\n<h2 id=\"使用方法\"><a href=\"#使用方法\" class=\"headerlink\" title=\"使用方法\"></a>使用方法</h2><h3 id=\"AT指令\"><a href=\"#AT指令\" class=\"headerlink\" title=\"AT指令\"></a>AT指令</h3><p>可以使用简单的AT指令实现一些比较常用的功能</p>\n<p><img src=\"https://image.wxydejoy.top/image/ESP32/20220610123118-2022-06-10.png\" alt=\"20220610123118-2022-06-10\"></p>\n<p>这里丢个链接<a href=\"https://docs.espressif.com/projects/esp-at/zh_CN/latest/esp32/AT_Binary_Lists/index.html\">AT 固件 - ESP32 -  — ESP-AT 用户指南 latest 文档</a></p>\n<h3 id=\"C-x2F-C-语言编程\"><a href=\"#C-x2F-C-语言编程\" class=\"headerlink\" title=\"C&#x2F;C++语言编程\"></a>C&#x2F;C++语言编程</h3><ol>\n<li>VScode</li>\n</ol>\n<p>不建议小白使用，网上例程少，上手慢。</p>\n<p>初次编译慢，但后续修改方便，配合上vscode的错误提示，还可。</p>\n<p>这个是我目前在用的，因为AT指令不能完全满足我的需求，所以只能自己敲代码了。</p>\n<p>当然你也可以选择arduino，不过我觉得它又丑又慢，而且我本身经常用vscode。</p>\n<p>通过官方插件，日常使用还是很不错的。</p>\n<p><img src=\"https://image.wxydejoy.top/image/ESP32/20220610123407-2022-06-10.png\" alt=\"20220610123407-2022-06-10\"></p>\n<ol>\n<li>Arduino</li>\n</ol>\n<p>每次修改都要完全重新编译。</p>\n<p>又丑又慢，不过胜在编程操作简单。</p>\n<p>而且网上有很多例程，可以借鉴，开发效率稍微高点，建议新手使用。</p>\n<h2 id=\"一些问题\"><a href=\"#一些问题\" class=\"headerlink\" title=\"一些问题\"></a>一些问题</h2><ol>\n<li>不建议使用esp32的ADC接口，精度较低。</li>\n<li>AT指令无法调试PWM，暂未找到解决办法。</li>\n<li>ESP32资源有限，只能用在小项目或者副芯片。</li>\n</ol>\n","categories":[{"name":"💻Code","path":"api/categories/💻Code.json"}],"tags":[{"name":"💻嵌入式","path":"api/tags/💻嵌入式.json"}]}